signalflow/__init__.py
signalflow/analytic/__init__.py
signalflow/analytic/base.py
signalflow/analytic/signals/__init__.py
signalflow/analytic/signals/signals_price.py
signalflow/analytic/strategy/__init__.py
signalflow/analytic/strategy/main_strategy_metrics.py
signalflow/core/__init__.py
signalflow/core/base_mixin.py
signalflow/core/decorators.py
signalflow/core/enums.py
signalflow/core/registry.py
signalflow/core/rolling_aggregator.py
signalflow/core/containers/__init__.py
signalflow/core/containers/order.py
signalflow/core/containers/portfolio.py
signalflow/core/containers/position.py
signalflow/core/containers/raw_data.py
signalflow/core/containers/raw_data_view.py
signalflow/core/containers/signals.py
signalflow/core/containers/strategy_state.py
signalflow/core/containers/trade.py
signalflow/core/signal_transforms/__init__.py
signalflow/core/signal_transforms/base_signal_transform.py
signalflow/data/__init__.py
signalflow/data/raw_data_factory.py
signalflow/data/raw_store/__init__.py
signalflow/data/raw_store/base.py
signalflow/data/raw_store/duckdb_stores.py
signalflow/data/source/__init__.py
signalflow/data/source/base.py
signalflow/data/source/binance.py
signalflow/data/strategy_store/__init__.py
signalflow/data/strategy_store/base.py
signalflow/data/strategy_store/duckdb.py
signalflow/data/strategy_store/schema.py
signalflow/detector/__init__.py
signalflow/detector/base.py
signalflow/detector/sma_cross.py
signalflow/detector/adapter/__init__.py
signalflow/detector/adapter/pandas_detector.py
signalflow/feature/__init__.py
signalflow/feature/base.py
signalflow/feature/examples.py
signalflow/feature/feature_pipeline.py
signalflow/feature/global_feature.py
signalflow/feature/offset_feature.py
signalflow/strategy/__init__.py
signalflow/strategy/broker/__init__.py
signalflow/strategy/broker/backtest.py
signalflow/strategy/broker/base.py
signalflow/strategy/broker/realtime_spot.py
signalflow/strategy/broker/executor/__init__.py
signalflow_trading-0.3.1.dist-info/licenses/LICENSE
signalflow_trading-0.3.1.dist-info/METADATA
signalflow_trading-0.3.1.dist-info/WHEEL
signalflow_trading-0.3.1.dist-info/top_level.txt
signalflow_trading-0.3.1.dist-info/RECORD
