Metadata-Version: 2.4
Name: signalflow-trading
Version: 0.3.1
Summary: SignalFlow: modular framework for trading signal generation, validation and execution
Author: pathway2nothing
License: MIT License
Project-URL: Homepage, https://signalflow-trading.com
Project-URL: Source, https://github.com/pathway2nothing/signalflow-trading
Project-URL: Issues, https://github.com/pathway2nothing/signalflow-trading/issues
Requires-Python: >=3.12
License-File: LICENSE
Requires-Dist: pandas>=2.0.0
Requires-Dist: polars>=0.20.0
Requires-Dist: duckdb>=1.0.0
Requires-Dist: loguru>=0.7.0
Requires-Dist: aiohttp>=3.9.0
Requires-Dist: scikit-learn>=1.3.0
Requires-Dist: optuna>=3.0.0
Requires-Dist: numba>=0.58.0
Requires-Dist: lightning>=2.1.0
Requires-Dist: numpy>=1.24.0
Requires-Dist: pandas-ta>=0.3.14b
Provides-Extra: docs
Requires-Dist: mkdocs>=1.6; extra == "docs"
Requires-Dist: mkdocs-material>=9.5; extra == "docs"
Requires-Dist: mkdocstrings[python]>=0.25; extra == "docs"
Requires-Dist: pymdown-extensions>=10.0; extra == "docs"
Requires-Dist: mkdocs-minify-plugin>=0.7.0; extra == "docs"
Requires-Dist: mike>=2.1.0; extra == "docs"
Requires-Dist: mkdocs-macros-plugin>=1.5.0; extra == "docs"
Dynamic: license-file
